frasco_github.py
setup.py
frasco_github.egg-info/PKG-INFO
frasco_github.egg-info/SOURCES.txt
frasco_github.egg-info/dependency_links.txt
frasco_github.egg-info/not-zip-safe
frasco_github.egg-info/requires.txt
frasco_github.egg-info/top_level.txt