Metadata-Version: 1.0
Name: frasco-github
Version: 0.3
Summary: Github integration for Frasco
Home-page: http://github.com/frascoweb/frasco-github
Author: Maxime Bouroumeau-Fuseau
Author-email: maxime.bouroumeau@gmail.com
License: MIT
Platform: any
